__init__.py
main.py
inixx-0.1.0.dist-info/METADATA
inixx-0.1.0.dist-info/WHEEL
inixx-0.1.0.dist-info/top_level.txt
inixx-0.1.0.dist-info/RECORD
