Metadata-Version: 2.4
Name: inixx
Version: 0.1.0
Summary: Clustering validation metrics like Dunn Index and Silhouette Score.
Author-email: Yuvraj <yuvrajbiswalofficial@gmail.com>
Project-URL: Homepage, https://github.com/Yuvraj-cyborg/inixx
Project-URL: Bug Tracker, https://github.com/Yuvraj-cyborg/inixx/issues
Classifier: Programming Language :: Python :: 3
Classifier: License :: OSI Approved :: MIT License
Classifier: Operating System :: OS Independent
Classifier: Intended Audience :: Science/Research
Classifier: Topic :: Scientific/Engineering
Requires-Python: >=3.8
